py_active_win.cpython-38-darwin.so
py_active_window-0.0.1.dist-info/RECORD
py_active_window-0.0.1.dist-info/LICENSE
py_active_window-0.0.1.dist-info/WHEEL
py_active_window-0.0.1.dist-info/top_level.txt
py_active_window-0.0.1.dist-info/METADATA
